a11y_mcp/__init__.py
a11y_mcp/server.py
a11y_mcp/accessibility/__init__.py
a11y_mcp/accessibility/report.py
a11y_mcp/accessibility/scanner.py
a11y_mcp/browser/__init__.py
a11y_mcp/browser/manager.py
a11y_mcp/assets/axe.min.js
a11y_mcp-0.1.1.dist-info/METADATA
a11y_mcp-0.1.1.dist-info/WHEEL
a11y_mcp-0.1.1.dist-info/entry_points.txt
a11y_mcp-0.1.1.dist-info/licenses/LICENSE
a11y_mcp-0.1.1.dist-info/RECORD
