Metadata-Version: 2.4
Name: a11y-mcp
Version: 0.1.1
Summary: MCP server for accessibility testing with Cloudflare bypass using Camoufox and axe-core
Project-URL: Homepage, https://github.com/antonio-rmrz/a11y-mcp
Project-URL: Repository, https://github.com/antonio-rmrz/a11y-mcp
Project-URL: Documentation, https://github.com/antonio-rmrz/a11y-mcp#readme
Project-URL: Issues, https://github.com/antonio-rmrz/a11y-mcp/issues
Project-URL: Changelog, https://github.com/antonio-rmrz/a11y-mcp/blob/main/CHANGELOG.md
Author: Antonio Ramirez
License: MIT
License-File: LICENSE
Keywords: a11y,accessibility,automation,axe-core,cloudflare,deque,mcp,model-context-protocol,testing,wcag
Classifier: Development Status :: 4 - Beta
Classifier: Intended Audience :: Developers
Classifier: License :: OSI Approved :: MIT License
Classifier: Operating System :: OS Independent
Classifier: Programming Language :: Python :: 3
Classifier: Programming Language :: Python :: 3.10
Classifier: Programming Language :: Python :: 3.11
Classifier: Programming Language :: Python :: 3.12
Classifier: Programming Language :: Python :: 3.13
Classifier: Topic :: Internet :: WWW/HTTP
Classifier: Topic :: Software Development :: Quality Assurance
Classifier: Topic :: Software Development :: Testing
Requires-Python: >=3.10
Requires-Dist: camoufox[geoip]>=0.4.0
Requires-Dist: jinja2>=3.0
Requires-Dist: mcp>=1.2.0
Requires-Dist: pydantic>=2.0
Provides-Extra: dev
Requires-Dist: build>=1.0.0; extra == 'dev'
Requires-Dist: pytest-asyncio>=0.21; extra == 'dev'
Requires-Dist: pytest>=7.0; extra == 'dev'
Requires-Dist: ruff>=0.1.0; extra == 'dev'
Requires-Dist: twine>=4.0.0; extra == 'dev'
